backrefs/__init__.py
backrefs/__meta__.py
backrefs/_bre_parse.py
backrefs/_bregex_parse.py
backrefs/_bregex_typing.py
backrefs/bre.py
backrefs/bregex.py
backrefs/py.typed
backrefs/util.py
backrefs/uniprops/__init__.py
backrefs/uniprops/unidata/__init__.py
backrefs/uniprops/unidata/age.py
backrefs/uniprops/unidata/alias.py
backrefs/uniprops/unidata/bidiclass.py
backrefs/uniprops/unidata/bidipairedbrackettype.py
backrefs/uniprops/unidata/binary.py
backrefs/uniprops/unidata/block.py
backrefs/uniprops/unidata/canonicalcombiningclass.py
backrefs/uniprops/unidata/decompositiontype.py
backrefs/uniprops/unidata/eastasianwidth.py
backrefs/uniprops/unidata/generalcategory.py
backrefs/uniprops/unidata/graphemeclusterbreak.py
backrefs/uniprops/unidata/hangulsyllabletype.py
backrefs/uniprops/unidata/indicpositionalcategory.py
backrefs/uniprops/unidata/indicsyllabiccategory.py
backrefs/uniprops/unidata/joininggroup.py
backrefs/uniprops/unidata/joiningtype.py
backrefs/uniprops/unidata/linebreak.py
backrefs/uniprops/unidata/numerictype.py
backrefs/uniprops/unidata/numericvalue.py
backrefs/uniprops/unidata/quickcheck.py
backrefs/uniprops/unidata/script.py
backrefs/uniprops/unidata/scriptextensions.py
backrefs/uniprops/unidata/sentencebreak.py
backrefs/uniprops/unidata/verticalorientation.py
backrefs/uniprops/unidata/wordbreak.py
backrefs-6.0.dist-info/METADATA
backrefs-6.0.dist-info/WHEEL
backrefs-6.0.dist-info/licenses/LICENSE.md
backrefs-6.0.dist-info/RECORD
