Metadata-Version: 2.4
Name: backrefs
Version: 6.0
Summary: A wrapper around re and regex that adds additional back references.
Project-URL: Homepage, https://github.com/facelessuser/backrefs
Author-email: Isaac Muse <Isaac.Muse@gmail.com>
License-Expression: MIT
License-File: LICENSE.md
Keywords: re,regex
Classifier: Development Status :: 5 - Production/Stable
Classifier: Environment :: Console
Classifier: Intended Audience :: Developers
Classifier: License :: OSI Approved :: MIT License
Classifier: Operating System :: OS Independent
Classifier: Programming Language :: Python :: 3
Classifier: Programming Language :: Python :: 3.9
Classifier: Programming Language :: Python :: 3.10
Classifier: Programming Language :: Python :: 3.11
Classifier: Programming Language :: Python :: 3.12
Classifier: Programming Language :: Python :: 3.13
Classifier: Programming Language :: Python :: 3.14
Classifier: Topic :: Software Development :: Libraries :: Python Modules
Classifier: Typing :: Typed
Requires-Python: >=3.9
Provides-Extra: extras
Requires-Dist: regex; extra == 'extras'
